fragment/__init__.py
fragment/api.py
fragment/errors.py
fragment/helper.py
fragment/parser.py
fragment/py.typed
fragment/resources/__init__.py
fragment/resources/base.py
fragment/resources/usernames.py
fragment/type_hints.py
python_fragment-0.3.0.dist-info/LICENSE
python_fragment-0.3.0.dist-info/WHEEL
python_fragment-0.3.0.dist-info/METADATA
python_fragment-0.3.0.dist-info/RECORD
