Metadata-Version: 2.1
Name: python-fragment
Version: 0.3.0
Summary: Reverse engineered Fragment API that mimics the official webclient
Home-page: https://github.com/ren3104/python-fragment
License: MIT
Keywords: async,asyncio,fragment,ton,telegram
Author: ren3104
Author-email: 2ren3104@gmail.com
Requires-Python: >=3.8,<4.0
Classifier: License :: OSI Approved :: MIT License
Classifier: Operating System :: OS Independent
Classifier: Programming Language :: Python :: 3
Classifier: Programming Language :: Python :: 3.10
Classifier: Programming Language :: Python :: 3.8
Classifier: Programming Language :: Python :: 3.9
Classifier: Topic :: Software Development :: Libraries :: Python Modules
Classifier: Typing :: Typed
Requires-Dist: aiohttp (>=3.8.6,<4.0.0)
Requires-Dist: selectolax[cython] (>=0.3.17,<0.4.0)
Project-URL: Bug Tracker, https://github.com/ren3104/python-fragment/issues
Project-URL: Repository, https://github.com/ren3104/python-fragment
